various_api_tools-1.1.1.dist-info/METADATA
various_api_tools-1.1.1.dist-info/WHEEL
various_api_tools-1.1.1.dist-info/entry_points.txt
various_api_tools/__init__.py
various_api_tools/translators/__init__.py
various_api_tools/translators/json.py
various_api_tools/translators/psycopg/__init__.py
various_api_tools/translators/psycopg/base.py
various_api_tools/translators/psycopg/constants.py
various_api_tools/translators/psycopg/psycopg.py
various_api_tools/translators/psycopg/psycopg2.py
various_api_tools/translators/pydantic.py
various_api_tools/validators/__init__.py
various_api_tools/validators/pydantic/__init__.py
various_api_tools/validators/pydantic/constants.py
various_api_tools/validators/pydantic/utils.py
various_api_tools-1.1.1.dist-info/RECORD
