Metadata-Version: 2.1
Name: various-api-tools
Version: 1.1.1
Summary: A lightweight utility package for common API-related tasks in Python, including JSON and Pydantic error translators that provide user-friendly Russian messages.
Author-Email: dkurchigin <kurchigin.dmitry@yandex.ru>
License: MIT
Classifier: Programming Language :: Python :: 3
Classifier: Programming Language :: Python
Classifier: Typing :: Typed
Classifier: Programming Language :: Python :: 3 :: Only
Classifier: Programming Language :: Python :: 3.10
Classifier: Programming Language :: Python :: 3.11
Classifier: Programming Language :: Python :: 3.12
Classifier: Programming Language :: Python :: 3.13
Project-URL: Homepage, https://gitverse.ru/dkurchigin/various-api-tools
Project-URL: Documentation, https://various-api-tools.dkurchigin.ru/
Project-URL: Source, https://gitverse.ru/dkurchigin/various-api-tools
Requires-Python: >=3.10
Requires-Dist: pydantic>=2.12.3
Requires-Dist: email-validator>=2.3.0
